MLGeometry/__init__.py
MLGeometry/bihomoNN.py
MLGeometry/cicyhypersurface.py
MLGeometry/complex_math.py
MLGeometry/hypersurface.py
MLGeometry/lbfgs.py
MLGeometry/loss.py
MLGeometry/tf_dataset.py
mlgeometry_tf-1.2.2.dist-info/licenses/LICENSE
mlgeometry_tf-1.2.2.dist-info/METADATA
mlgeometry_tf-1.2.2.dist-info/WHEEL
mlgeometry_tf-1.2.2.dist-info/top_level.txt
mlgeometry_tf-1.2.2.dist-info/RECORD
