Metadata-Version: 2.4
Name: MLGeometry-tf
Version: 1.2.2
Summary: Higher dimensional computational geometry using machine learning software
Maintainer-email: Yidi Qi <qiyidi2012@gmail.com>
License: MIT License
Project-URL: Homepage, https://github.com/yidiq7/MLGeometry
Project-URL: Changelog, https://github.com/yidiq7/MLGeometry/blob/master/CHANGELOG.md
Requires-Python: >=3.11
License-File: LICENSE
Requires-Dist: tensorflow-probability[tf]
Requires-Dist: sympy
Requires-Dist: matplotlib
Dynamic: license-file
